sglabtools/__init__.py
sglabtools/augment.py
sglabtools/cli.py
sglabtools/count.py
sglabtools/mask.py
sglabtools/merge.py
sglabtools/plot.py
sglabtools/run_pipeline.py
sglabtools/transform.py
SGLab_tools-1.0.3.dist-info/METADATA
SGLab_tools-1.0.3.dist-info/WHEEL
SGLab_tools-1.0.3.dist-info/entry_points.txt
SGLab_tools-1.0.3.dist-info/top_level.txt
SGLab_tools-1.0.3.dist-info/RECORD
