Metadata-Version: 2.1
Name: SGLab-tools
Version: 1.0.3
Summary: Outils CLI pour l’analyse comparative de génomes bactériens
Home-page: https://github.com/EtienneNtumba/SGLab-tools
Author: Etienne Ntumba Kabongo
Author-email: etienne.ntumba.kabongo@umontreal.ca
Classifier: Programming Language :: Python :: 3
Classifier: License :: OSI Approved :: MIT License
Classifier: Operating System :: OS Independent
Requires-Python: >=3.8
Requires-Dist: typer >=0.9
Requires-Dist: pandas
Requires-Dist: biopython
Requires-Dist: matplotlib
Requires-Dist: seaborn
Requires-Dist: openpyxl
